LICENSE
README.md
pyproject.toml
setup.py
neslab/bonito/__init__.py
neslab/bonito/bisection.py
neslab/bonito/distributions.py
neslab/bonito/protocols.py
neslab/bonito/pwr2time.py
neslab_bonito.egg-info/PKG-INFO
neslab_bonito.egg-info/SOURCES.txt
neslab_bonito.egg-info/dependency_links.txt
neslab_bonito.egg-info/entry_points.txt
neslab_bonito.egg-info/requires.txt
neslab_bonito.egg-info/top_level.txt