Metadata-Version: 2.1
Name: neslab-bonito
Version: 1.0.3
Summary: Implementation of the Bonito connection protocol for battery-free devices
Home-page: https://bonito.nes-lab.org
Author: Kai Geissdoerfer
Author-email: kai.geissdoerfer@tu-dresden.de
License: MIT
Platform: UNKNOWN
Provides-Extra: examples
License-File: LICENSE
